flexify/__init__.py
flexify/hello.py
flexify/core/__init__.py
flexify/core/control_flow.py
flexify/core/exceptions.py
flexify/core/module.py
flexify/core/param_info.py
flexify/core/status.py
flexify/registry/__init__.py
flexify/registry/module_registry.py
flexify/runner/__init__.py
flexify/runner/models.py
flexify/runner/runner.py
flexify/runner/simple_runner.py
flexify-0.1.0.dist-info/METADATA
flexify-0.1.0.dist-info/WHEEL
flexify-0.1.0.dist-info/licenses/LICENSE
flexify-0.1.0.dist-info/RECORD
