Metadata-Version: 2.4
Name: flexify
Version: 0.1.0
Summary: Add your description here
License-File: LICENSE
Requires-Python: >=3.10
Requires-Dist: pyyaml>=6.0
Provides-Extra: dev
Requires-Dist: pytest-cov>=4.1.0; extra == 'dev'
Requires-Dist: pytest>=8.0.0; extra == 'dev'
